{"v":5,"entries":{"helpers-gridbackground--primary":{"type":"story","id":"helpers-gridbackground--primary","name":"Primary","title":"Helpers/GridBackground","importPath":"./stories/helpers/GridBackground.stories.tsx","componentPath":"./src/components","tags":["dev","test"]},"heros-aimessage--primary":{"type":"story","id":"heros-aimessage--primary","name":"Primary","title":"Heros/AIMessage","importPath":"./stories/heros/AIMessage.stories.tsx","componentPath":"./src/components","tags":["dev","test"]},"heros-humaninput--primary":{"type":"story","id":"heros-humaninput--primary","name":"Primary","title":"Heros/HumanInput","importPath":"./stories/heros/HumanInput.stories.tsx","componentPath":"./src/components","tags":["dev","test"]},"heros-humanmessage--primary":{"type":"story","id":"heros-humanmessage--primary","name":"Primary","title":"Heros/HumanMessage","importPath":"./stories/heros/HumanMessage.stories.tsx","componentPath":"./src/components","tags":["dev","test"]},"patterns-messages--primary":{"type":"story","id":"patterns-messages--primary","name":"Primary","title":"Patterns/Messages","importPath":"./stories/patterns/Messages.stories.tsx","componentPath":"./src/components","tags":["dev","test"]}}}
